{
  "bootnodes": [
    {
      "name": "Bootnode 1",
      "address": "replace-with-testnet-bootnode-address",
      "allocation": "replace-with-allocation",
      "stake": "replace-with-stake",
      "keys_location": "config/bootnode1/identity.json",
      "p2p_endpoint": "replace-with-snr-endpoint",
      "rpc_endpoint": "https://testnet-core-rpc.synergy-network.io"
    }
  ],
  "cluster": {
    "cluster_id": "replace-with-testnet-cluster-id",
    "name": "Testnet Bootstrap Cluster",
    "class": 1
  },
  "faucet": {
    "address": "replace-with-testnet-faucet-address",
    "allocation": "replace-with-allocation",
    "keys_location": "config/faucet/identity.json"
  },
  "treasury": {
    "address": "replace-with-testnet-treasury-address",
    "allocation": "replace-with-allocation",
    "keys_location": "config/treasury/identity.json"
  },
  "notes": "Copy to config/testnet_wallets.json only after generating fresh testnet identities."
}
